Last modified 24-Oct-2024; size 882 bytes
  SHA-256 checksum 8ab60f4414b6bf5a6b9f07281942280f714cd666e9a57a4787ac334d6780458b
  Compiled from "TextBook.java"
public class oldshelf.TextBook extends oldshelf.Book
  minor version: 0
  major version: 61
  flags: (0x0021) ACC_PUBLIC, ACC_SUPER
  this_class: #8                          // oldshelf/TextBook
  super_class: #2                         // oldshelf/Book
  interfaces: 0, fields: 1, methods: 3, attributes: 3
Constant pool:
   #1 = Methodref          #2.#3          // oldshelf/Book."<init>":(Ljava/lang/String;)V
   #2 = Class              #4             // oldshelf/Book
   #3 = NameAndType        #5:#6          // "<init>":(Ljava/lang/String;)V
   #4 = Utf8               oldshelf/Book
   #5 = Utf8               <init>
   #6 = Utf8               (Ljava/lang/String;)V
   #7 = Fieldref           #8.#9          // oldshelf/TextBook.subject:Ljava/lang/String;
   #8 = Class              #10            // oldshelf/TextBook
   #9 = NameAndType        #11:#12        // subject:Ljava/lang/String;
  #10 = Utf8               oldshelf/TextBook
  #11 = Utf8               subject
  #12 = Utf8               Ljava/lang/String;
  #13 = InvokeDynamic      #0:#14         // #0:makeConcatWithConstants:(Ljava/lang/String;)Ljava/lang/String;
  #14 = NameAndType        #15:#16        // makeConcatWithConstants:(Ljava/lang/String;)Ljava/lang/String;
  #15 = Utf8               makeConcatWithConstants
  #16 = Utf8               (Ljava/lang/String;)Ljava/lang/String;
  #17 = Utf8               Code
  #18 = Utf8               LineNumberTable
  #19 = Utf8               getSubject
  #20 = Utf8               ()Ljava/lang/String;
  #21 = Utf8               toString
  #22 = Utf8               SourceFile
  #23 = Utf8               TextBook.java
  #24 = Utf8               BootstrapMethods
  #25 = MethodHandle       6:#26          // REF_invokeStatic java/lang/invoke/StringConcatFactory.makeConcatWithConstants:(Ljava/lang/invoke/MethodHandles$Lookup;Ljava/lang/String;Ljava/lang/invoke/MethodType;Ljava/lang/String;[Ljava/lang/Object;)Ljava/lang/invoke/CallSite;
  #26 = Methodref          #27.#28        // java/lang/invoke/StringConcatFactory.makeConcatWithConstants:(Ljava/lang/invoke/MethodHandles$Lookup;Ljava/lang/String;Ljava/lang/invoke/MethodType;Ljava/lang/String;[Ljava/lang/Object;)Ljava/lang/invoke/CallSite;
  #27 = Class              #29            // java/lang/invoke/StringConcatFactory
  #28 = NameAndType        #15:#30        // makeConcatWithConstants:(Ljava/lang/invoke/MethodHandles$Lookup;Ljava/lang/String;Ljava/lang/invoke/MethodType;Ljava/lang/String;[Ljava/lang/Object;)Ljava/lang/invoke/CallSite;
  #29 = Utf8               java/lang/invoke/StringConcatFactory
  #30 = Utf8               (Ljava/lang/invoke/MethodHandles$Lookup;Ljava/lang/String;Ljava/lang/invoke/MethodType;Ljava/lang/String;[Ljava/lang/Object;)Ljava/lang/invoke/CallSite;
  #31 = String             #32            // TextBook{subject=\'\u0001\'}
  #32 = Utf8               TextBook{subject=\'\u0001\'}
  #33 = Utf8               InnerClasses
  #34 = Class              #35            // java/lang/invoke/MethodHandles$Lookup
  #35 = Utf8               java/lang/invoke/MethodHandles$Lookup
  #36 = Class              #37            // java/lang/invoke/MethodHandles
  #37 = Utf8               java/lang/invoke/MethodHandles
  #38 = Utf8               Lookup
{
  private final java.lang.String subject;
    descriptor: Ljava/lang/String;
    flags: (0x0012) ACC_PRIVATE, ACC_FINAL

  public oldshelf.TextBook(java.lang.String);
    descriptor: (Ljava/lang/String;)V
    flags: (0x0001) ACC_PUBLIC
    Code:
      stack=2, locals=2, args_size=2
         0: aload_0
         1: aload_1
         2: invokespecial #1                  // Method oldshelf/Book."<init>":(Ljava/lang/String;)V
         5: aload_0
         6: aload_1
         7: putfield      #7                  // Field subject:Ljava/lang/String;
        10: return
      LineNumberTable:
        line 8: 0
        line 9: 5
        line 10: 10

  public java.lang.String getSubject();
    descriptor: ()Ljava/lang/String;
    flags: (0x0001) ACC_PUBLIC
    Code:
      stack=1, locals=1, args_size=1
         0: aload_0
         1: getfield      #7                  // Field subject:Ljava/lang/String;
         4: areturn
      LineNumberTable:
        line 13: 0

  public java.lang.String toString();
    descriptor: ()Ljava/lang/String;
    flags: (0x0001) ACC_PUBLIC
    Code:
      stack=1, locals=1, args_size=1
         0: aload_0
         1: getfield      #7                  // Field subject:Ljava/lang/String;
         4: invokedynamic #13,  0             // InvokeDynamic #0:makeConcatWithConstants:(Ljava/lang/String;)Ljava/lang/String;
         9: areturn
      LineNumberTable:
        line 18: 0
}
SourceFile: "TextBook.java"
BootstrapMethods:
  0: #25 REF_invokeStatic java/lang/invoke/StringConcatFactory.makeConcatWithConstants:(Ljava/lang/invoke/MethodHandles$Lookup;Ljava/lang/String;Ljava/lang/invoke/MethodType;Ljava/lang/String;[Ljava/lang/Object;)Ljava/lang/invoke/CallSite;
    Method arguments:
      #31 TextBook{subject=\'\u0001\'}
InnerClasses:
  public static final #38= #34 of #36;    // Lookup=class java/lang/invoke/MethodHandles$Lookup of class java/lang/invoke/MethodHandles